<record><title-alt-script>מבול : צווייטער טייל פון דער טרילאגיע</title-alt-script><volume>2</volume><creator-alt-script>שענקעוויטש, הענריק</creator-alt-script><title>Mabl tsṿeyṭer ṭeyl fun der ṭrilogye</title><creator>Sienkiewicz, Henryk, 1846-1916</creator><creator>Bleyshifṭ, Mosheh</creator><language>yid</language><publisher>Ṿarshe : Ḥ. Bzshoza</publisher><date>1926</date><addeddate>2009-01-28 07:48:15</addeddate><imagecount>278</imagecount><identifier>nybc203891</identifier><identifier-access>http://www.archive.org/details/nybc203891</identifier-access><identifier-ark>ark:/13960/t4hm5j88q</identifier-ark><spielberg_number>203924</spielberg_number></record>