<record><collection>spielberg</collection><title-alt-script>אהין : ראמאן</title-alt-script><creator-alt-script>שניאור, ז</creator-alt-script><title>Ahin roman</title><creator>Shneour, Zalman, 1886-1959</creator><language>yid</language><publisher>Berlin : Yalḳuṭ</publisher><date>1923</date><addeddate>2009-01-15 12:06:27</addeddate><imagecount>194</imagecount><identifier>nybc202089</identifier><identifier-access>http://www.archive.org/details/nybc202089</identifier-access><identifier-ark>ark:/13960/t70v8s33p</identifier-ark><marc_url>http://www.archive.org/download/nybc202089/nybc202089_marc.xml</marc_url><spielberg_number>202089</spielberg_number></record>