<record><title-alt-script>יידישע טיפן אין דער פוילישער ליטעראטור</title-alt-script><creator-alt-script>ווילטשינסקי, ה</creator-alt-script><title>Yidishe ṭipn in der Poylisher liṭeraṭur</title><creator>Ṿilṭshinsḳi, Yeḥezḳel, 1893-1943</creator><language>yiddish</language><subject>"214535"</subject><publisher>Kulṭur-lige</publisher><date>[1928]</date><addeddate>2009-10-02 19:30:32</addeddate><imagecount>244</imagecount><identifier>yidishetipnind00vi</identifier><identifier-access>http://www.archive.org/details/yidishetipnind00vi</identifier-access><identifier-ark>ark:/13960/t7wm1tm5s</identifier-ark><theme>"214535"</theme></record>