<record><title-alt-script>די ליעבע פראווינץ</title-alt-script><creator-alt-script>גארעליק, ש</creator-alt-script><title>Di liebe proṿints</title><creator>Gorelik, Sch. (Schmarja), 1877-1942</creator><language>yid</language><subject>Jews</subject><publisher>Ṿilna : B.A. Ḳletsḳin</publisher><date>1911</date><imagecount>150</imagecount><identifier>nybc206602</identifier><identifier-access>http://www.archive.org/details/nybc206602</identifier-access><identifier-ark>ark:/13960/t0zp4b28s</identifier-ark><spielberg_number>206602</spielberg_number></record>