<record><collection>spielberg</collection><title-alt-script>יידיש : צווייטער קונטרוס</title-alt-script><creator-alt-script>שטענצל, א.נ</creator-alt-script><title>Yidish tsṿeyṭer ḳuntrus</title><creator>Stencl, Abraham Nahum, b. 1897</creator><language>yid</language><publisher>London : Y. Naroditsḳi</publisher><date>1942</date><addeddate>2009-01-15 12:44:02</addeddate><imagecount>70</imagecount><identifier>nybc202925</identifier><identifier-access>http://www.archive.org/details/nybc202925</identifier-access><identifier-ark>ark:/13960/t5j96fp77</identifier-ark><marc_url>http://www.archive.org/download/nybc202925/nybc202925_marc.xml</marc_url><spielberg_number>202925</spielberg_number></record>