<record><title-alt-script>יודישע געשיכטע : ניי בעארבייט נאך פראפעסאר גרעץ און אנדערע קוועלען</title-alt-script><volume>2</volume><creator-alt-script>לייזעראוויטש, י. ל</creator-alt-script><title>Yudishe geshikhṭe nay bearbeyṭ nokh Profesor Grets un andere ḳṿelen</title><creator>Leyzeroṿiṭsh, Y. E. (Yitsḥaḳ Eliezer), 1883-1927</creator><creator>Graetz, Heinrich, 1817-1891</creator><creator>Zeitlin, Hillel, 1871-1942</creator><creator>Karlinsky, Ber, 1886-1935</creator><language>yid</language><subject>Jews</subject><publisher>Ṿarsha : Ferlag B. Shimin</publisher><date>1911</date><addeddate>2009-01-17 07:00:11</addeddate><imagecount>394</imagecount><identifier>nybc204385</identifier><identifier-access>http://www.archive.org/details/nybc204385</identifier-access><identifier-ark>ark:/13960/t7kp8996k</identifier-ark><spielberg_number>204384</spielberg_number><theme>History.</theme><theme>Jews</theme></record>