<record><title-alt-script>דער אנהייב : דערציילונגען</title-alt-script><creator-alt-script>אורבאס, יהושע</creator-alt-script><title>Der onheyb dertseylungen.</title><creator>Urbas, Joshua</creator><language>yid</language><publisher>Ṭoronṭo : Iḳuf</publisher><date>1970</date><imagecount>160</imagecount><identifier>nybc205429</identifier><identifier-access>http://www.archive.org/details/nybc205429</identifier-access><identifier-ark>ark:/13960/t8v98fc25</identifier-ark><spielberg_number>205429</spielberg_number></record>