<record><title-alt-script>די כוזרים : היסטארישער ראמאן</title-alt-script><creator-alt-script>ראזענבערג, שלמה</creator-alt-script><title>Di Kuzrim hisṭorisher roman</title><creator>Rosenberg, Shloyme, 1896-1975</creator><language>yid</language><publisher>Buenos-Ayres : Yidbukh</publisher><date>1960</date><imagecount>364</imagecount><identifier>nybc210040</identifier><identifier-access>http://www.archive.org/details/nybc210040</identifier-access><identifier-ark>ark:/13960/t8pc38z00</identifier-ark><spielberg_number>210040</spielberg_number></record>