<record><title-alt-script>חנה סענעש : און אנדערע דערציילונגען</title-alt-script><creator-alt-script>ברידזשער, דוד</creator-alt-script><title>Ḥana Senesh un andere dertseylungen</title><creator>Bridger, David, 1907-</creator><language>yid</language><subject>Senesh, Hannah, 1921-1944</subject><publisher>Meḳsiḳe : Yidishe shul in Meḳsiḳe</publisher><date>1960</date><imagecount>66</imagecount><identifier>nybc211846</identifier><identifier-access>http://www.archive.org/details/nybc211846</identifier-access><identifier-ark>ark:/13960/t5m90hw16</identifier-ark><spielberg_number>211846</spielberg_number></record>