<record><title-alt-script>אמעריקא : זאמלבוך</title-alt-script><title>Ameriḳa zamelbukh</title><creator>Wortsmann, Ezekiel, 1878-</creator><language>yid</language><publisher>Nuyorḳ : Natsyonale biblioṭheḳ</publisher><date>1909</date><addeddate>2009-01-15 13:15:57</addeddate><imagecount>50</imagecount><identifier>nybc203663</identifier><identifier-access>http://www.archive.org/details/nybc203663</identifier-access><identifier-ark>ark:/13960/t8hd84d1b</identifier-ark><spielberg_number>203663</spielberg_number></record>