<record><title-alt-script>מיינע אוניווערסיטעטן</title-alt-script><creator-alt-script>גארקי, מאקסים</creator-alt-script><title>Mayne uniṿersiṭeṭn</title><creator>Gorky, Maksim, 1868-1936</creator><language>yid</language><subject>Gorky, Maksim, 1868-1936</subject><publisher>Ṿilne : B. Ḳletsḳin</publisher><date>1928</date><addeddate>2009-01-28 08:24:17</addeddate><imagecount>364</imagecount><identifier>nybc206613</identifier><identifier-access>http://www.archive.org/details/nybc206613</identifier-access><identifier-ark>ark:/13960/t9j392k23</identifier-ark><spielberg_number>206613</spielberg_number><series>Geḳlibene ṿerḳ ;</series><theme>Gorky, Maksim, 1868-1936</theme></record>