<record><title-alt-script>אלע ווערק</title-alt-script><volume>17</volume><creator-alt-script>מענדעלע מוכר-ספרים</creator-alt-script><title>Ale ṿerḳ</title><creator>Mendele Mokher Sefarim, 1835-1917</creator><creator>Mayzel, Nachman, 1887-1966</creator><language>yid</language><publisher>Ṿarsha : Mendele</publisher><date>1928</date><imagecount>184</imagecount><identifier>nybc202712</identifier><identifier-access>http://www.archive.org/details/nybc202712</identifier-access><identifier-ark>ark:/13960/t9q246n3f</identifier-ark><spielberg_number>202696</spielberg_number></record>