<record><collection>spielberg</collection><title-alt-script>אין קאמף פאר א אידישער מלוכה</title-alt-script><creator-alt-script>צייטלין,אהרן</creator-alt-script><title>In ḳamf far a Idisher melukhe</title><creator>Zeitlin, Aaron, 1898-1973</creator><language>yid</language><subject>Zionism</subject><publisher>Nyu Yorḳ : Aroysgegebn funm Idish-natsyonaln arbeṭer farband</publisher><date>1943</date><addeddate>2009-01-18 07:28:38</addeddate><imagecount>34</imagecount><identifier>nybc211998</identifier><identifier-access>http://www.archive.org/details/nybc211998</identifier-access><identifier-ark>ark:/13960/t9668rb95</identifier-ark><marc_url>http://www.archive.org/download/nybc211998/nybc211998_marc.xml</marc_url><spielberg_number>211998</spielberg_number><theme>Zionism.</theme></record>