<record><title-alt-script>ווונדן און ווונדער</title-alt-script><creator-alt-script>שווארץ, שלמה</creator-alt-script><title>Ṿundn un ṿunder</title><creator>Schwartz, Shloime, 1907-1988</creator><language>yid</language><publisher>Tel-Aviv : ha-Menorah</publisher><date>1975</date><addeddate>2009-01-28 09:08:36</addeddate><imagecount>162</imagecount><identifier>nybc210300</identifier><identifier-access>http://www.archive.org/details/nybc210300</identifier-access><identifier-ark>ark:/13960/t7jq18s3c</identifier-ark><spielberg_number>210300</spielberg_number></record>