<record><collection>spielberg</collection><title-alt-script>א קולטורעלע אנטוויקלונג פאליסי פאר קוויבעק</title-alt-script><title>A ḳulṭurele anṭṿiḳlung polisi far Ḳṿibeḳ</title><language>yid</language><publisher>Québec : Èditeur officiel</publisher><date>1978</date><addeddate>2012-11-12 18:03:41</addeddate><imagecount>56</imagecount><identifier>nybc212714</identifier><identifier-access>http://archive.org/details/nybc212714</identifier-access><identifier-ark>ark:/13960/t07w7p86b</identifier-ark><marc_url>None</marc_url><theme>Jewish sermons, Yiddish.</theme></record>