<record><collection>spielberg</collection><title-alt-script>בלויע האריזאנטן</title-alt-script><creator-alt-script>אוסטרי-דן, ישעיהו</creator-alt-script><title>Bloye horizonṭn</title><creator>Austridan, Yeshayahu, 1912-</creator><language>yid</language><publisher>Meḳsiḳe : Di shṭime</publisher><date>1945</date><addeddate>2009-01-17 15:26:55</addeddate><imagecount>210</imagecount><identifier>nybc205526</identifier><identifier-access>http://www.archive.org/details/nybc205526</identifier-access><identifier-ark>ark:/13960/t3vt1xz93</identifier-ark><marc_url>http://www.archive.org/download/nybc205526/nybc205526_marc.xml</marc_url><spielberg_number>205526</spielberg_number></record>