<record><title-alt-script>אלטע וועגען : לידער</title-alt-script><creator-alt-script>העללער, זעליג</creator-alt-script><title>Alṭe ṿegen lider</title><creator>Heller, Selig, 1894-1969</creator><language>yid</language><publisher>Shiḳago : L. M. Shṭeyn</publisher><date>1926</date><imagecount>216</imagecount><identifier>nybc207157</identifier><identifier-access>http://www.archive.org/details/nybc207157</identifier-access><identifier-ark>ark:/13960/t6057vc1k</identifier-ark><spielberg_number>207157</spielberg_number></record>