<record><collection>spielberg</collection><title-alt-script>פון א וויט לאנד : דערציילונגען פון טשילענער יידישען און אלגעמיינעם לעבן</title-alt-script><volume>2</volume><creator-alt-script>גאלדשיין, יוסף</creator-alt-script><title>Fun a ṿayṭ land dertseylungen fun tshilener Yidishn un algemaynem lebn</title><creator>Goldchain, Jose</creator><language>yid</language><publisher>Sanṭyago, Ṭshile : Sh. Sul</publisher><date>1949</date><addeddate>2009-01-17 20:12:08</addeddate><imagecount>66</imagecount><identifier>nybc206498</identifier><identifier-access>http://www.archive.org/details/nybc206498</identifier-access><identifier-ark>ark:/13960/t14m9gj2v</identifier-ark><marc_url>http://www.archive.org/download/nybc206498/nybc206498_marc.xml</marc_url><spielberg_number>204698</spielberg_number></record>