<record><title-alt-script>בלומען : טעקסטען פון לידער צו זינגען אין די אידישע שולען</title-alt-script><title>Blumen ṭeḳsṭen fun lider tsu zingen in di Idishe shulen</title><creator>Leṿin, Yaaḳov, 1884-1958</creator><language>yid</language><subject>Children's poetry, Yiddish</subject><publisher>Nyu-Yorḳ : Idishe shul</publisher><date>1920</date><imagecount>130</imagecount><identifier>nybc205154</identifier><identifier-access>http://www.archive.org/details/nybc205154</identifier-access><identifier-ark>ark:/13960/t75t3xk9t</identifier-ark><spielberg_number>205154</spielberg_number></record>