<record><collection>spielberg</collection><title-alt-script>אינגעלע רינגעלע : די טשיקאווע וואנדערלאכע געשיכטע פון א אינגעלע מיט א רינגעלע</title-alt-script><title>Yingele ringele di ṭshiḳaṿe ṿunderlakhe geshikhṭe fun a yingele miṭ a ringele...</title><creator>Bassein, Leon, 1879-1928</creator><creator>Gudlman, Aharon</creator><language>yid</language><subject>Children's stories, Yiddish</subject><publisher>Nyu Yorḳ : Matoneʹs</publisher><date>1929</date><addeddate>2009-01-13 10:55:12</addeddate><imagecount>204</imagecount><identifier>nybc200960</identifier><identifier-access>http://www.archive.org/details/nybc200960</identifier-access><identifier-ark>ark:/13960/t05x2mf34</identifier-ark><marc_url>http://www.archive.org/download/nybc200960/nybc200960_marc.xml</marc_url><spielberg_number>200960</spielberg_number><theme>Children's stories, Yiddish.</theme></record>