<record><title-alt-script>אויסגעוויילטע ווערק</title-alt-script><creator-alt-script>רייזען, אברהם</creator-alt-script><title>Oysgeveylṭe ṿerḳ</title><creator>Reisen, Abraham, 1876-1953</creator><language>yid</language><publisher>Ṿarshe : Yidish bukh</publisher><date>1964</date><imagecount>466</imagecount><identifier>nybc203351</identifier><identifier-access>http://www.archive.org/details/nybc203351</identifier-access><identifier-ark>ark:/13960/t7qn6dv45</identifier-ark><spielberg_number>203351</spielberg_number></record>