<record><title-alt-script>א ניי לעבן : דערציילונגען</title-alt-script><creator-alt-script>קאפע, רבקה</creator-alt-script><title>A nay lebn dertseylungen</title><creator>Kopé, Rivka</creator><language>yid</language><publisher>Pariz : [o. fg.]</publisher><date>1959</date><imagecount>160</imagecount><identifier>nybc202603</identifier><identifier-access>http://www.archive.org/details/nybc202603</identifier-access><identifier-ark>ark:/13960/t2g73p96f</identifier-ark><spielberg_number>202603</spielberg_number></record>