<record><title-alt-script>שמועסנ וועגנ לעניניזמ</title-alt-script><creator-alt-script>קארפינסקי, וו</creator-alt-script><title>Shmuesn ṿegn Leninizm</title><creator>Karpinskiĭ, V. A. (Vi︠a︡cheslav Alekseevich), 1880-1965</creator><language>yid</language><publisher>Mosḳṿe : Emes</publisher><date>1934</date><addeddate>2009-01-18 05:55:36</addeddate><imagecount>494</imagecount><identifier>nybc211058</identifier><identifier-access>http://www.archive.org/details/nybc211058</identifier-access><identifier-ark>ark:/13960/t9086k048</identifier-ark><spielberg_number>211058</spielberg_number></record>