<record><title-alt-script>דער אינטערנאציאנאלער ארבעטער ארדן אין אידישן לעבן</title-alt-script><creator-alt-script>זאלצמאן, ר</creator-alt-script><title>Der inṭernatsyonaln arbeṭer ordn in Idishn lebn</title><creator>Zaltsman, R. (Reʼuven)</creator><language>yid</language><subject>Jewish Peoples Fraternal Order of the I.W.O. (U.S.)</subject><subject>Jews</subject><subject>Jewish communists</subject><publisher>[Nyu Yorḳ?] : Aroysgegeben fun der Natsyonaler Eḳezḳuṭive fun der Idisher seḳtsye, Inṭernatsyonaler arbeṭer orden</publisher><date>1938</date><imagecount>66</imagecount><identifier>nybc211276</identifier><identifier-access>http://www.archive.org/details/nybc211276</identifier-access><identifier-ark>ark:/13960/t45q57249</identifier-ark><spielberg_number>211276</spielberg_number></record>