<record><title-alt-script>פיזיק</title-alt-script><creator-alt-script>פאלייעוו, ג. י</creator-alt-script><creator-alt-script>פיארישקינ, א. וו</creator-alt-script><title>Fiziḳ</title><creator>Faleev, G. I. (Grigoriĭ Ivanovich)</creator><creator>Përyshkin, A. V. (Aleksandr Vasilʹevich)</creator><language>yid</language><subject>Physics</subject><publisher>Ḳiyeṿ ; Kharḳoṿ : Melukhe-farlag far di natsyonale minderhayṭn in USR'R</publisher><date>1935</date><imagecount>190</imagecount><identifier>nybc211130</identifier><identifier-access>http://www.archive.org/details/nybc211130</identifier-access><identifier-ark>ark:/13960/t50g3zh4c</identifier-ark><spielberg_number>211130</spielberg_number><additional_author_transcribed>פיארישקינ, א. וו.</additional_author_transcribed></record>