<record><title-alt-script>קינדער פון אקעאן</title-alt-script><creator-alt-script>פיטש-פערקיס, ל</creator-alt-script><title>Ḳinder fun oḳean</title><creator>Perkins, Lucy Fitch, 1865-1937</creator><creator>Shapiro, Monye, 1898-1931</creator><language>yid</language><publisher>Ḳiyeṿ : Ḳulṭur lige</publisher><date>1929</date><imagecount>102</imagecount><identifier>nybc213351</identifier><identifier-access>http://www.archive.org/details/nybc213351</identifier-access><identifier-ark>ark:/13960/t75t3xp0t</identifier-ark><spielberg_number>213351</spielberg_number><series>Shul un piyonern biblyoṭeḳ ;</series></record>