<record><collection>spielberg</collection><title-alt-script>דרייסיק יאר י. ל. פרץ שול</title-alt-script><title>Draysiḳ yor Y. L. Perets shul</title><language>yid</language><publisher>Ṿinipeg : [s.n.]</publisher><date>1944</date><addeddate>2012-03-13 16:05:07</addeddate><imagecount>158</imagecount><identifier>nybc211918</identifier><identifier-access>http://archive.org/details/nybc211918</identifier-access><identifier-ark>ark:/13960/t2h71hh92</identifier-ark><marc_url>None</marc_url><theme>Jewish theater</theme><theme>Periodicals.</theme></record>