<record><collection>spielberg</collection><title-alt-script>אויף יענער זייט אקעאן</title-alt-script><creator-alt-script>גלאזמאן, ברוך</creator-alt-script><title>Oyf yener zayṭ oḳean</title><creator>Glasman, Baruch, 1893-1945</creator><language>yid</language><publisher>Ṿilne : B. Ḳletsḳin</publisher><date>1928</date><addeddate>2009-01-17 20:37:40</addeddate><imagecount>280</imagecount><identifier>nybc206729</identifier><identifier-access>http://www.archive.org/details/nybc206729</identifier-access><identifier-ark>ark:/13960/t3pv6sh7b</identifier-ark><marc_url>http://www.archive.org/download/nybc206729/nybc206729_marc.xml</marc_url><spielberg_number>206729</spielberg_number><series>Geḳlibene ṿerḳ ;</series></record>