<record><collection>spielberg</collection><title-alt-script>דער משוגענער פילאזאף אין ענגלאנד : צושלאגענע געדאנקען, בילדער, ווערטער און חקירות  דעם פיאזאף'ס לעבענס-געשיכטע</title-alt-script><volume>2</volume><creator-alt-script>ווינטשעווסקי, מארריס</creator-alt-script><title>Der meshugener filozof in England tsushlogene gedanḳen, bilder, ṿerṭer un ḥḳires̀ ; dem filozof's lebens-geshikhṭe</title><creator>Winchevsky, Morris, b. 1856</creator><language>yid</language><publisher>Nyu Yorḳ : Forṿerṭs</publisher><date>1920</date><addeddate>2009-01-28 08:45:16</addeddate><imagecount>386</imagecount><identifier>nybc207465</identifier><identifier-access>http://www.archive.org/details/nybc207465</identifier-access><identifier-ark>ark:/13960/t7br93d7t</identifier-ark><marc_url>http://www.archive.org/download/nybc207465/nybc207465_marc.xml</marc_url><spielberg_number>207464</spielberg_number></record>