<record><title-alt-script>ייד און וועלט</title-alt-script><creator-alt-script>זשיטלאווסקי, חיים</creator-alt-script><title>Yid un ṿelṭ</title><creator>Zhitlowsky, Chaim, 1865-1943</creator><creator>Mayzel, Nachman, 1887-1966</creator><language>yid</language><subject>Jewish nationalism</subject><subject>Jews</subject><publisher>Nyu-Yorḳ : Alṿelṭlekher Yidisher Ḳulṭur-farband, Dr. Ḥayim Zshiṭloṿsḳi-Folḳs-Ḳomiṭeṭ</publisher><date>1945</date><addeddate>2009-01-13 10:37:52</addeddate><imagecount>326</imagecount><identifier>nybc200597</identifier><identifier-access>http://www.archive.org/details/nybc200597</identifier-access><identifier-ark>ark:/13960/t57d35m2q</identifier-ark><spielberg_number>200597</spielberg_number><series>Ale ṿerḳ ;</series><theme>Identity.</theme><theme>Jewish nationalism.</theme><theme>Jews</theme></record>