<record><title-alt-script>מאני לייב</title-alt-script><creator-alt-script>מאני לייב</creator-alt-script><title>Mani Leyb</title><creator>Mani Leib, 1883-1953</creator><creator>Simon, Solomon, 1895-</creator><creator>Shṭern, Yiśraʼel</creator><creator>Shainblum, Yechiel</creator><language>yid</language><subject>Mani Leib, 1883-1953</subject><publisher>Monṭreal : Yidishe shul</publisher><date>1975</date><imagecount>38</imagecount><identifier>nybc205021</identifier><identifier-access>http://www.archive.org/details/nybc205021</identifier-access><identifier-ark>ark:/13960/t18k7m36r</identifier-ark><spielberg_number>205021</spielberg_number></record>