<record><title-alt-script>ארבעטלוינ, פרייז אונ רעוועכ</title-alt-script><creator-alt-script>מארקס, קארל</creator-alt-script><title>Arbeṭloyn, prayz un reṿekh</title><creator>Marx, Karl, 1818-1883</creator><language>yid</language><subject>Value</subject><subject>Wages</subject><publisher>Mosḳṿe : Emes</publisher><date>1934</date><imagecount>78</imagecount><identifier>nybc210701</identifier><identifier-access>http://www.archive.org/details/nybc210701</identifier-access><identifier-ark>ark:/13960/t30294t04</identifier-ark><spielberg_number>210701</spielberg_number></record>