<record><title-alt-script>דער רעדאקטאר : ראמאן</title-alt-script><creator-alt-script>האמסון, קנוט</creator-alt-script><title>Der redaḳṭor roman</title><creator>Hamsun, Knut, 1859-1952</creator><language>yid</language><subject>Norwegian literature</subject><publisher>Ṿarsha : "ha-Tsefirah"</publisher><date>1911</date><addeddate>2009-01-18 07:00:09</addeddate><imagecount>248</imagecount><identifier>nybc211595</identifier><identifier-access>http://www.archive.org/details/nybc211595</identifier-access><identifier-ark>ark:/13960/t6d227428</identifier-ark><spielberg_number>211595</spielberg_number><theme>Norwegian literature</theme><theme>Translations into Yiddish.</theme></record>