<record><title-alt-script>קודש וחול אין דער יידישער מוזיק</title-alt-script><creator-alt-script>פאטער, יששכר</creator-alt-script><title>Ḳodesh ṿe-ḥol in der Yidisher muziḳ</title><creator>Fater, Isaschar, 1912-</creator><language>yid</language><subject>Synagogue music</subject><subject>Jews</subject><publisher>[Tel Aviv] : H. Leyṿiḳ farlag baym Fareyn fun Yidishe shraybers un zshornalisṭn in Yiśroel</publisher><date>1988</date><imagecount>312</imagecount><identifier>nybc205016</identifier><identifier-access>http://www.archive.org/details/nybc205016</identifier-access><identifier-ark>ark:/13960/t7cr63z37</identifier-ark><spielberg_number>205016</spielberg_number></record>