<record><title-alt-script>געשיכטעס : מייסעלעכ אונ פאעמעס</title-alt-script><creator-alt-script>פינינבערג, עזרא</creator-alt-script><title>Geshikhṭes</title><creator>Fininberg, Ezra, 1899-1946</creator><language>yiddish</language><subject>"216177"</subject><publisher>Melukhe-farlag "Der emes"</publisher><date>1939</date><addeddate>2009-10-05 12:11:21</addeddate><imagecount>200</imagecount><identifier>geshikhtes00fini</identifier><identifier-access>http://www.archive.org/details/geshikhtes00fini</identifier-access><identifier-ark>ark:/13960/t8v98pm83</identifier-ark><theme>Folklore.</theme><theme>Jews</theme></record>