<record><title-alt-script>אונטער די בלויע ארגענטינער הימלען : יהודית : ראמאן</title-alt-script><volume>1</volume><creator-alt-script>גוטמאן, גאלדע</creator-alt-script><title>Unṭer di bloye Argenṭiner himlen Yehudis̀ : roman</title><creator>Guṭman, Golde, 1906-</creator><language>yid</language><publisher>Buenos-Ayres : [o.fg.]</publisher><date>1954</date><imagecount>186</imagecount><identifier>nybc206661</identifier><identifier-access>http://www.archive.org/details/nybc206661</identifier-access><identifier-ark>ark:/13960/t2h70q80p</identifier-ark><spielberg_number>206661</spielberg_number></record>