<record><title-alt-script>ספר תורת חיים</title-alt-script><creator-alt-script>מאלאד, חיים</creator-alt-script><title>Sefer torat ḥayim ...</title><creator>Molod, Hyman L.</creator><language>yid</language><publisher>[Nyu-Yorḳ] : [H. Molod]</publisher><date>1956</date><addeddate>2012-03-13 16:05:54</addeddate><imagecount>160</imagecount><identifier>nybc211922</identifier><identifier-access>http://archive.org/details/nybc211922</identifier-access><identifier-ark>ark:/13960/t0wq12d53</identifier-ark></record>