<record><title-alt-script>דאר-איס, דאר-איין</title-alt-script><creator-alt-script>מארקיש, פערעץ</creator-alt-script><title>Dor-oys, dor-ayn</title><creator>Markish, Peretz, 1895-1952</creator><language>yid</language><publisher>[Kharkov] : Melikhe-farlag fun Uḳayne</publisher><date>1929</date><imagecount>392</imagecount><identifier>nybc210689</identifier><identifier-access>http://www.archive.org/details/nybc210689</identifier-access><identifier-ark>ark:/13960/t0qr53v64</identifier-ark><spielberg_number>210689</spielberg_number></record>