<record><collection>spielberg</collection><title-alt-script>לעבן און אומקום אין ביאליסטאקער געטא</title-alt-script><creator-alt-script>קלעמענטינאווסקי, ד</creator-alt-script><title>Lebn un umḳum in Byalostoḳer geṭo</title><creator>Klementinowski, D. (David), 1888-1961</creator><language>yid</language><publisher>Nyu-Yorḳ : [o. fg.]</publisher><date>1946</date><addeddate>2009-01-18 03:39:17</addeddate><imagecount>98</imagecount><identifier>nybc209902</identifier><identifier-access>http://www.archive.org/details/nybc209902</identifier-access><identifier-ark>ark:/13960/t8w95g94t</identifier-ark><marc_url>http://www.archive.org/download/nybc209902/nybc209902_marc.xml</marc_url><spielberg_number>209902</spielberg_number></record>