<record><title-alt-script>דער פשוטער חלום</title-alt-script><creator-alt-script>קאץ, מעינקע</creator-alt-script><title>Der posheṭer ḥolem</title><creator>Katz, Menke, 1906-1991</creator><language>yid</language><publisher>Nyu-Yorḳ : [o.fg.]</publisher><date>1947</date><addeddate>2009-01-13 09:49:00</addeddate><imagecount>184</imagecount><identifier>nybc200055</identifier><identifier-access>http://www.archive.org/details/nybc200055</identifier-access><identifier-ark>ark:/13960/t8tb1dc7j</identifier-ark><spielberg_number>200055</spielberg_number></record>