<record><title-alt-script>מדינת ישראל און דער וואטיקאן</title-alt-script><creator-alt-script>זאקוסקי, א. י</creator-alt-script><title>Medines̀ Yiśroel un der Ṿaṭiḳan</title><creator>Zacusky, Aaron Joel, 1909-</creator><language>yid</language><subject>Catholic Church</subject><publisher>Buenos-Ayres : Alṿelṭlekher Yidisher ḳulṭur-ḳongres, Argenṭiner opṭeyl</publisher><date>1974</date><addeddate>2009-01-17 22:28:32</addeddate><imagecount>50</imagecount><identifier>nybc207574</identifier><identifier-access>http://www.archive.org/details/nybc207574</identifier-access><identifier-ark>ark:/13960/t1jh3v827</identifier-ark><spielberg_number>207574</spielberg_number><theme>Catholic Church</theme></record>