<record><title-alt-script>וועגנ דערלערנענ לענינס ווערק</title-alt-script><creator-alt-script>אדאראטסקי, וו</creator-alt-script><title>Ṿegn derlernen Lenin's ṿerḳ</title><creator>Adoratskiĭ, V. V. (Vladimir Viktorovich), 1878-</creator><creator>Lenin, Vladimir Il'ich, 1870-1924</creator><language>yid</language><publisher>Minsḳ : Melukhe-farlag fun Ṿaysrusland Yidseḳṭer</publisher><date>1932</date><addeddate>2009-01-18 05:53:05</addeddate><imagecount>46</imagecount><identifier>nybc210986</identifier><identifier-access>http://www.archive.org/details/nybc210986</identifier-access><identifier-ark>ark:/13960/t3kw5pw4m</identifier-ark><spielberg_number>210986</spielberg_number></record>