<record><title-alt-script>מרימל : דראמאטישער ציקל אין פופצן בילדער</title-alt-script><creator-alt-script>ארצישעווסקא, טעא</creator-alt-script><title>Miryaml dramaṭisher tsiḳl in fuftsn bilder</title><creator>Arciszewska, Tea, d. 1962</creator><language>yid</language><publisher>Pariz : Goldene paṿe</publisher><date>1959</date><imagecount>238</imagecount><identifier>nybc205975</identifier><identifier-access>http://www.archive.org/details/nybc205975</identifier-access><identifier-ark>ark:/13960/t7cr63z75</identifier-ark><spielberg_number>205975</spielberg_number></record>