<record><collection>spielberg</collection><title-alt-script>מיין וועג אהיים : מעמוארן פון אן אסיר-ציון אין ראטן-פארבאנד</title-alt-script><creator-alt-script>ראזין, אהרון</creator-alt-script><title>Mayn ṿeg aheym memuarn fun an asir-Tsiyon in Roṭn-Farband</title><creator>Rozin, Aharon, 1910-</creator><language>yid</language><subject>Rozin, Aharon, 1910-</subject><subject>Zionists</subject><subject>Jews</subject><subject>Political prisoners</subject><publisher>Yerushalayim : Dr. S. un R. Hurvits Fond bay der Yidisher Kultur-Gezelshaft in Yerushalayim</publisher><date>1981</date><addeddate>2009-01-18 03:59:57</addeddate><imagecount>386</imagecount><identifier>nybc210025</identifier><identifier-access>http://www.archive.org/details/nybc210025</identifier-access><identifier-ark>ark:/13960/t2x35310b</identifier-ark><marc_url>http://www.archive.org/download/nybc210025/nybc210025_marc.xml</marc_url><spielberg_number>210025</spielberg_number><theme>Biography.</theme><theme>Jews</theme><theme>Political prisoners</theme><theme>Soviet Union</theme><theme>Zionists</theme></record>