<record><collection>spielberg</collection><title-alt-script>יוסף ראטנבערג : צו זיין ערשטער יארצייט</title-alt-script><title>Yosef Roṭnberg tsu zayn ershṭer yortsayṭ</title><language>yid</language><publisher>[Tel-Aviv] : Y.L. Perets</publisher><date>1961</date><addeddate>2009-01-15 11:57:50</addeddate><imagecount>210</imagecount><identifier>nybc201841</identifier><identifier-access>http://www.archive.org/details/nybc201841</identifier-access><identifier-ark>ark:/13960/t89g5z12h</identifier-ark><marc_url>http://www.archive.org/download/nybc201841/nybc201841_marc.xml</marc_url><spielberg_number>201841</spielberg_number></record>