<record><collection>spielberg</collection><title-alt-script>רעזאלוציעס פון 5טן קאנגרעס און קאנסטיטוציע פון קאמוניסטישן אינטערנאציאנאל</title-alt-script><title>Rezolutsyes fun 5ṭn ḳongres un ḳonsṭiṭutsye fun Ḳomunisṭishn inṭernatsyonal</title><creator>Communist International. Congress</creator><language>yid</language><publisher>Nyu Yorḳ : Idishe federatsye ṿorḳers parṭey</publisher><date>1924</date><addeddate>2009-01-17 07:46:50</addeddate><imagecount>66</imagecount><identifier>nybc204893</identifier><identifier-access>http://www.archive.org/details/nybc204893</identifier-access><identifier-ark>ark:/13960/t6m04dd97</identifier-ark><marc_url>http://www.archive.org/download/nybc204893/nybc204893_marc.xml</marc_url><spielberg_number>204893</spielberg_number></record>