<record><collection>spielberg</collection><title-alt-script>מענש און תורה</title-alt-script><volume>1</volume><creator-alt-script>שניצער, י. ל</creator-alt-script><title>Mensh un Toyre</title><creator>Snitzer, Jacob Lazarus, b. 1874</creator><language>yid</language><subject>Jewish sermons, Yiddish</subject><publisher>Nuyorḳ, N.Y. : Pardes</publisher><date>1938</date><addeddate>2009-01-18 06:41:37</addeddate><imagecount>258</imagecount><identifier>nybc211484</identifier><identifier-access>http://www.archive.org/details/nybc211484</identifier-access><identifier-ark>ark:/13960/t9f47zm1g</identifier-ark><marc_url>http://www.archive.org/download/nybc211484/nybc211484_marc.xml</marc_url><spielberg_number>211484</spielberg_number><theme>Jewish sermons, Yiddish.</theme></record>