<record><title-alt-script>מאזעסוויל : די ערשטע יידישע קאלאניע אין ארגענטינע</title-alt-script><creator-alt-script>שענדעריי, מ</creator-alt-script><title>Mozesṿil di ershṭe Yidishe ḳolonye in Argenṭine tsu di 75 yor zinṭ ir grindung 1889-1964</title><creator>Senderey, M. (Moisés)</creator><creator>Gabis, Abraham</creator><language>yid</language><subject>Jews</subject><publisher>Buenos-Ayres : [s.n.]</publisher><date>1964</date><addeddate>2009-01-18 06:38:40</addeddate><imagecount>90</imagecount><identifier>nybc211397</identifier><identifier-access>http://www.archive.org/details/nybc211397</identifier-access><identifier-ark>ark:/13960/t4bp0cj2k</identifier-ark><spielberg_number>211397</spielberg_number><theme>Argentina</theme><theme>History.</theme><theme>Jews</theme></record>