<record><collection>spielberg</collection><title-alt-script>מעמוארען</title-alt-script><volume>3</volume><creator-alt-script>פיגנער, ווערא</creator-alt-script><title>Memuaren</title><creator>Figner, Vera, 1852-1942</creator><language>yid</language><subject>Figner, Vera, 1852-1942</subject><subject>Shlisselʹburgskai︠a︡ ti︠u︡rʹma</subject><subject>Nihilism</subject><subject>Women revolutionaries</subject><publisher>Nyu Yorḳ : Ṿeḳer</publisher><date>1925</date><addeddate>2009-01-18 02:34:41</addeddate><imagecount>218</imagecount><identifier>nybc209452</identifier><identifier-access>http://www.archive.org/details/nybc209452</identifier-access><identifier-ark>ark:/13960/t7xk8m91z</identifier-ark><marc_url>http://www.archive.org/download/nybc209452/nybc209452_marc.xml</marc_url><spielberg_number>209450</spielberg_number><theme>Biography.</theme><theme>Nihilism.</theme><theme>Soviet Union</theme><theme>Women revolutionaries</theme></record>