<record><collection>spielberg</collection><title-alt-script>די פרוי פון די באריקאדן : אקטאבער</title-alt-script><creator-alt-script>רייסנער, לאריסא</creator-alt-script><title>Di froy fun di bariḳadn Oḳṭober</title><creator>Reĭsner, Larisa, 1895-1926</creator><creator>Raḳoṿsḳa, Puah, 1865-1955</creator><language>yid</language><publisher>Ṿarshe : S. Goldfarb</publisher><date>1929</date><addeddate>2009-01-15 11:49:51</addeddate><imagecount>504</imagecount><identifier>nybc201607</identifier><identifier-access>http://www.archive.org/details/nybc201607</identifier-access><identifier-ark>ark:/13960/t3st7w43p</identifier-ark><marc_url>http://www.archive.org/download/nybc201607/nybc201607_marc.xml</marc_url><spielberg_number>201607</spielberg_number></record>