<record><collection>spielberg</collection><title-alt-script>דער וואונדערלאכער לייב</title-alt-script><creator-alt-script>פאט, יעקב</creator-alt-script><title>Der ṿunderlakher leyb</title><creator>Pat, Jacob, 1890-1966</creator><language>yid</language><publisher>Ṿarshe : A. Giṭlin</publisher><date>1921</date><addeddate>2009-01-18 07:47:22</addeddate><imagecount>22</imagecount><identifier>nybc212802</identifier><identifier-access>http://www.archive.org/details/nybc212802</identifier-access><identifier-ark>ark:/13960/t5v69qv09</identifier-ark><marc_url>http://www.archive.org/download/nybc212802/nybc212802_marc.xml</marc_url><spielberg_number>212802</spielberg_number></record>