<record><collection>spielberg</collection><title-alt-script>די נייסטע ווערק</title-alt-script><volume>2</volume><creator-alt-script>נאדיר, משה</creator-alt-script><title>Di naysṭe ṿerḳ</title><creator>Nadir, Moishe, 1885-1943</creator><language>yid</language><subject>Yiddish literature</subject><publisher>Nyu-York : Morgn Frayhayṭ</publisher><date>1931</date><addeddate>2009-01-18 01:04:12</addeddate><imagecount>248</imagecount><identifier>nybc208756</identifier><identifier-access>http://www.archive.org/details/nybc208756</identifier-access><identifier-ark>ark:/13960/t9k363529</identifier-ark><marc_url>http://www.archive.org/download/nybc208756/nybc208756_marc.xml</marc_url><spielberg_number>208755</spielberg_number><theme>Yiddish literature.</theme></record>