<record><collection>spielberg</collection><title-alt-script>וועגן ים און יבשה</title-alt-script><creator-alt-script>נאוואגרודסקי, י</creator-alt-script><title>Ṿegn yam un yabosheh</title><creator>Novogrudskiĭ, David Moiseevich, 1898-1953</creator><language>yid</language><subject>Science</subject><subject>Ocean</subject><publisher>Byalisṭoḳ : Ḳulṭur-lige</publisher><date>1920</date><addeddate>2009-01-18 08:49:53</addeddate><imagecount>38</imagecount><identifier>nybc213179</identifier><identifier-access>http://www.archive.org/details/nybc213179</identifier-access><identifier-ark>ark:/13960/t0ks7092n</identifier-ark><marc_url>http://www.archive.org/download/nybc213179/nybc213179_marc.xml</marc_url><spielberg_number>213179</spielberg_number><theme>Juvenile literature.</theme><theme>Ocean</theme><theme>Science</theme></record>