<record><collection>spielberg</collection><title-alt-script>גאונים און גדולים: ביאגראפיעס : לעבענס-בעשרייבונגען פון אלע גאומים און גדילים פון אידישען פאלק</title-alt-script><title>Geoynim un gdoylim : biografyes : lebens beshraybungen fun ale geoynim un gdoylim fun Idishen folḳ</title><language>yid</language><publisher>New York : Star Hebrew Book Co.</publisher><date>[192-?]</date><addeddate>2011-12-06 21:57:48</addeddate><imagecount>612</imagecount><identifier>nybc204987</identifier><identifier-access>http://www.archive.org/details/nybc204987</identifier-access><identifier-ark>ark:/13960/t2j68h102</identifier-ark><marc_url>None</marc_url></record>