<record><collection>spielberg</collection><title-alt-script>אידיליען און בילדער</title-alt-script><creator-alt-script>סטאווסקי, משה</creator-alt-script><title>Idilyen un bilder</title><creator>Stavsky, Moses</creator><language>yid</language><publisher>Ṿarsha : Ṿelṭ biblioṭeḳ</publisher><date>1912</date><addeddate>2012-08-10 18:17:25</addeddate><imagecount>90</imagecount><identifier>nybc212517</identifier><identifier-access>http://archive.org/details/nybc212517</identifier-access><identifier-ark>ark:/13960/t4th9sc49</identifier-ark><marc_url>None</marc_url></record>