<record><title-alt-script>ספר ילקוט יוסף : געלקיבענע מאמרים פון תלמוד, מדרשים ילקוט א. א</title-alt-script><creator-alt-script>לעוו, ישראל יוסף</creator-alt-script><title>Sefer Yalḳuṭ Yosef geḳlibene maymorim fun Talmud, medroshim, Yalḳuṭ A. A. ...</title><creator>Lew, J</creator><language>yid</language><subject>Bible</subject><subject>Talmud</subject><subject>Aggada</subject><publisher>London : [o. fg.]</publisher><date>1947</date><imagecount>196</imagecount><identifier>nybc204585</identifier><identifier-access>http://www.archive.org/details/nybc204585</identifier-access><identifier-ark>ark:/13960/t4dn4f80n</identifier-ark><spielberg_number>204585</spielberg_number></record>