<record><title-alt-script>צוויי משפחות : ראמאן</title-alt-script><volume>2</volume><creator-alt-script>פינער, י</creator-alt-script><title>Tsvey mishpoḥes̀ roman</title><creator>Finer, Y. (Yitsḥaḳ), 1908-</creator><language>yid</language><publisher>[Tel-Aviv] : Y.L. Perets</publisher><date>1971</date><imagecount>418</imagecount><identifier>nybc209479</identifier><identifier-access>http://www.archive.org/details/nybc209479</identifier-access><identifier-ark>ark:/13960/t5n87jf8s</identifier-ark><spielberg_number>204039</spielberg_number></record>