<record><collection>spielberg</collection><title-alt-script>געזאמלטע שריפטן</title-alt-script><volume>5</volume><creator-alt-script>רייזען, אברהם</creator-alt-script><title>Gezamlṭe shrifṭn</title><creator>Reisen, Abraham, 1876-1953</creator><language>yid</language><publisher>Nyu Yorḳ : Frayhayṭ</publisher><date>1928</date><addeddate>2009-01-18 04:22:37</addeddate><imagecount>258</imagecount><identifier>nybc210201</identifier><identifier-access>http://www.archive.org/details/nybc210201</identifier-access><identifier-ark>ark:/13960/t7sn0gq70</identifier-ark><marc_url>http://www.archive.org/download/nybc210201/nybc210201_marc.xml</marc_url><spielberg_number>210197</spielberg_number></record>