<record><collection>spielberg</collection><title-alt-script>אין טיגל : ראמאן פון ישראל-לעבן</title-alt-script><creator-alt-script>חיין-שמעוני, ל</creator-alt-script><title>In ṭigl roman fun Yiśroel-lebn</title><creator>Chain-Shimoni, L., 1900-1974</creator><language>yid</language><publisher>Tel-Aviv : Y.L. Perets</publisher><date>1974</date><addeddate>2009-01-15 12:53:00</addeddate><imagecount>274</imagecount><identifier>nybc203177</identifier><identifier-access>http://www.archive.org/details/nybc203177</identifier-access><identifier-ark>ark:/13960/t9b56vt5w</identifier-ark><marc_url>http://www.archive.org/download/nybc203177/nybc203177_marc.xml</marc_url><spielberg_number>203177</spielberg_number></record>