<record><title-alt-script>משניות, מיט נקודות</title-alt-script><volume>6</volume><creator-alt-script>פיעטרושקא, שמחה</creator-alt-script><title>Mishnayes̀, miṭ niḳudes̀</title><creator>Pietruszka, Symcha, 1893-1950</creator><language>yid</language><publisher>Nyu Yorḳ : Gilead</publisher><date>1955</date><addeddate>2009-01-18 01:02:49</addeddate><imagecount>642</imagecount><identifier>nybc208723</identifier><identifier-access>http://www.archive.org/details/nybc208723</identifier-access><identifier-ark>ark:/13960/t1wd4565z</identifier-ark><spielberg_number>208718</spielberg_number></record>