<record><collection>spielberg</collection><title-alt-script>ענגשאפט : א שפיעל אין איין אקט</title-alt-script><creator-alt-script>ראוז, דזשעין</creator-alt-script><title>Engshafṭ a shpiel in eyn aḳṭ</title><creator>Rose, Jane</creator><language>yid</language><publisher>New York : M.N. Mayzel</publisher><date>1918</date><addeddate>2009-01-28 07:36:40</addeddate><imagecount>38</imagecount><identifier>nybc201710</identifier><identifier-access>http://www.archive.org/details/nybc201710</identifier-access><identifier-ark>ark:/13960/t2m61t81c</identifier-ark><marc_url>http://www.archive.org/download/nybc201710/nybc201710_marc.xml</marc_url><spielberg_number>201710</spielberg_number></record>