<record><collection>spielberg</collection><title-alt-script>מיט בילדער, פאקסימילן, געקליבעענע פערזענלעכע בריוו</title-alt-script><volume>6</volume><creator-alt-script></creator-alt-script><title>Ale ṿerḳ miṭ bilder, faḳsimiln, geḳlibene perzenlekhe briṿ</title><creator>Peretz, Isaac Leib, 1851 or 2-1915</creator><creator>Botoshansky, Jacob, 1895-</creator><language>yid</language><publisher>Buenos Ayres : Yidish</publisher><date>1944</date><addeddate>2009-01-18 02:29:35</addeddate><imagecount>212</imagecount><identifier>nybc209330</identifier><identifier-access>http://www.archive.org/details/nybc209330</identifier-access><identifier-ark>ark:/13960/t5v69qt2t</identifier-ark><marc_url>http://www.archive.org/download/nybc209330/nybc209330_marc.xml</marc_url><spielberg_number>209325</spielberg_number></record>