<record><title-alt-script>א רייזע בעשרייבונג פון בנימין דעם דריטער</title-alt-script><creator-alt-script>מענדעלע מוכר ספרים</creator-alt-script><title>A rayze beshraybung fun Binyomin dem driṭer</title><creator>Mendele Mokher Sefarim</creator><language>yid</language><publisher>Bruḳlin : Hibru Pob. Ḳo.</publisher><date>19--?</date><addeddate>2013-05-30 19:55:24</addeddate><imagecount>106</imagecount><identifier>nybc214527</identifier><identifier-access>http://archive.org/details/nybc214527</identifier-access><identifier-ark>ark:/13960/t4rj62k4w</identifier-ark><theme>Orthography and spelling.</theme><theme>Yiddish language</theme></record>