<record><collection>spielberg</collection><title-alt-script>אין קאמף פאר באדן : באדן-פאליטיק און קאלאניזאציע אין ארץ-ישראל און דער יידישער ארבעטער</title-alt-script><creator-alt-script>גרשוני, ג</creator-alt-script><title>In ḳamf far bodn bodn-poliṭiḳ un ḳolonizatsye in ertsiśroel un der Yidisher arbeṭer</title><creator>Gerszuni, Gershon, 1900-1959</creator><language>yid</language><publisher>Tel-Aviv : Naye ḳulṭur</publisher><date>1940</date><addeddate>2009-01-15 12:38:24</addeddate><imagecount>102</imagecount><identifier>nybc202769</identifier><identifier-access>http://www.archive.org/details/nybc202769</identifier-access><identifier-ark>ark:/13960/t54f22z8w</identifier-ark><marc_url>http://www.archive.org/download/nybc202769/nybc202769_marc.xml</marc_url><spielberg_number>202769</spielberg_number></record>