<record><title-alt-script>אין די מלינער וועלטן : נאוועלע</title-alt-script><creator-alt-script>גארעליק, פ</creator-alt-script><title>In di mliner ṿelṭn noṿele</title><creator>Gorelik, P</creator><language>yid</language><publisher>Tel-Aviv : Y. l. Perets</publisher><date>1960</date><addeddate>2009-01-28 08:24:15</addeddate><imagecount>442</imagecount><identifier>nybc206599</identifier><identifier-access>http://www.archive.org/details/nybc206599</identifier-access><identifier-ark>ark:/13960/t6057vp5j</identifier-ark><spielberg_number>206599</spielberg_number></record>