<record><title-alt-script>וועלטגעשיכטע פון אוראלטע צייטען ביז היינטיגען טאג</title-alt-script><volume>2</volume><creator-alt-script>פאגט, י. ג</creator-alt-script><title>Ṿelṭgeshikhṭe fun uralṭer tsayṭen biz haynṭigen ṭog</title><creator>Fogt, Y. G</creator><creator>Harkavy, Alexander, 1863-1939</creator><creator>Rozenberg, A. H</creator><language>yid</language><publisher>Nyu Yorḳ : Hibru Pob. Ḳo.</publisher><date>1918</date><addeddate>2009-01-18 02:32:16</addeddate><imagecount>442</imagecount><identifier>nybc209390</identifier><identifier-access>http://www.archive.org/details/nybc209390</identifier-access><identifier-ark>ark:/13960/t7br93388</identifier-ark><spielberg_number>209389</spielberg_number></record>