<record><title-alt-script>אין שאטן פון דורות : קינדהייט</title-alt-script><creator-alt-script>נחתומי, אברהם</creator-alt-script><title>In shoṭn fun doyres̀ ḳindhayṭ</title><creator>Naḥtomi, Avraham, 1900-1978</creator><language>yid</language><subject>Jewish actors</subject><publisher>Buenos Ayres : Tsenṭral-farband fun Poylishe Yidn in Argenṭine</publisher><date>1948</date><imagecount>194</imagecount><identifier>nybc200648</identifier><identifier-access>http://www.archive.org/details/nybc200648</identifier-access><identifier-ark>ark:/13960/t3ws8zs4g</identifier-ark><spielberg_number>200648</spielberg_number></record>