<record><title-alt-script>דער תלמוד און זיינע פערזענלעכקייטן</title-alt-script><creator-alt-script>מלכי, דוד</creator-alt-script><title>Der Talmud un zayne perzenlekhḳayṭn</title><creator>Malki, Daṿid, 1899-</creator><language>yid</language><subject>Talmud</subject><publisher>Pariz : [o.fg]</publisher><date>1964</date><addeddate>2009-01-18 00:59:04</addeddate><imagecount>350</imagecount><identifier>nybc208639</identifier><identifier-access>http://www.archive.org/details/nybc208639</identifier-access><identifier-ark>ark:/13960/t8sb4cm4n</identifier-ark><spielberg_number>208639</spielberg_number><theme>Talmud</theme></record>