<record><collection>spielberg</collection><title-alt-script>ליכט אין אונדזער לעבן</title-alt-script><creator-alt-script>שטאלפער, ה.א</creator-alt-script><title>Likhṭ in undzer lebn</title><creator>Shṭolper, H. A</creator><language>yid</language><publisher>[Buḳareshṭ] : Farlag far liṭeraṭur un ḳunsṭ funem shrayber-farband in R.F.D.</publisher><date>1951</date><addeddate>2009-01-15 12:28:14</addeddate><imagecount>78</imagecount><identifier>nybc202609</identifier><identifier-access>http://www.archive.org/details/nybc202609</identifier-access><identifier-ark>ark:/13960/t6057v925</identifier-ark><marc_url>http://www.archive.org/download/nybc202609/nybc202609_marc.xml</marc_url><spielberg_number>202609</spielberg_number></record>