<record><title-alt-script>קונסט אלס פארגעפיל פון מאכט</title-alt-script><creator-alt-script>שאץ-אנין, מ</creator-alt-script><title>Ḳunsṭ als fargefil fun makhṭ</title><creator>Shat︠s︡-Anin, Maks Urʹevich, 1885-1975</creator><language>yid</language><subject>Art</subject><publisher>Rige : [o. fg.]</publisher><date>1924</date><imagecount>54</imagecount><identifier>nybc211950</identifier><identifier-access>http://www.archive.org/details/nybc211950</identifier-access><identifier-ark>ark:/13960/t8kd2689k</identifier-ark><spielberg_number>211950</spielberg_number></record>