<record><collection>spielberg</collection><title-alt-script>וויין, וואסער און טרערן</title-alt-script><creator-alt-script>גולדברג, אליעזר</creator-alt-script><title>Wine, water and tears</title><creator>Goldberg, Eliezer</creator><language>yid</language><publisher>New York : E. Nelson</publisher><date>1984</date><addeddate>2012-02-02 19:29:55</addeddate><imagecount>168</imagecount><identifier>nybc202872</identifier><identifier-access>http://www.archive.org/details/nybc202872</identifier-access><identifier-ark>ark:/13960/t5bc51s53</identifier-ark><marc_url>None</marc_url><theme>History and criticism.</theme><theme>Yiddish literature</theme></record>