<record><title-alt-script>אלע ווערק</title-alt-script><volume>4</volume><creator-alt-script>שלום עליכם</creator-alt-script><title>Ale ṿerḳ</title><creator>Sholem Aleichem, 1859-1916</creator><language>yid</language><publisher>Nyu Yorḳ : Sholem-Aleykhem folḳsfond</publisher><date>1917</date><addeddate>2009-01-13 09:49:12</addeddate><imagecount>258</imagecount><identifier>nybc200075</identifier><identifier-access>http://www.archive.org/details/nybc200075</identifier-access><identifier-ark>ark:/13960/t84j0sh4x</identifier-ark><spielberg_number>200072</spielberg_number></record>