<record><title-alt-script>מיגעל סאכאראוו : פערציק יאר צו דינסט דער קאאפעראטציע</title-alt-script><creator-alt-script>ביזבערג, פנחס</creator-alt-script><title>Migel Sakharoṿ fertsiḳ yor tsu dinsṭ der ḳooperatsye ...</title><creator>Bizberg, Pedro, 1899-</creator><language>yid</language><subject>Sajaroff, Miguel</subject><subject>Jews</subject><subject>Agriculture, Cooperative</subject><publisher>Buenos Ayres : Aroysgegbn fun di Idish-ḳolonisṭishe ḳooperaṭiṿes, ongeshlosene in der fraṭernidad agrarya</publisher><date>1940</date><addeddate>2009-01-15 11:42:39</addeddate><imagecount>258</imagecount><identifier>nybc201383</identifier><identifier-access>http://www.archive.org/details/nybc201383</identifier-access><identifier-ark>ark:/13960/t9w09c36j</identifier-ark><spielberg_number>201383</spielberg_number><theme>Agriculture, Cooperative</theme><theme>Argentina.</theme><theme>Jews</theme></record>